openstack_publicdns/__init__.py
openstack_publicdns/designate/__init__.py
openstack_publicdns/designate/storage.py
openstack_publicdns/neutron/__init__.py
openstack_publicdns/neutron/dhcp.py
openstack_publicdns/neutron/dns.py
openstack_publicdns-0.0.6.dist-info/COPYING
openstack_publicdns-0.0.6.dist-info/METADATA
openstack_publicdns-0.0.6.dist-info/WHEEL
openstack_publicdns-0.0.6.dist-info/entry_points.txt
openstack_publicdns-0.0.6.dist-info/top_level.txt
openstack_publicdns-0.0.6.dist-info/RECORD
