Metadata-Version: 2.1
Name: openstack-publicdns
Version: 0.0.6
Summary: OpenStack public DNS plugins
Home-page: https://github.com/unipartdigital/openstack-publicdns
Author: Unipart Digital
Author-email: sysadmins@unipart.io
License: Apache
Platform: UNKNOWN
Classifier: Environment :: OpenStack
Classifier: Intended Audience :: Information Technology
Classifier: Intended Audience :: System Administrators
Classifier: License :: OSI Approved :: Apache Software License
Classifier: Operating System :: POSIX :: Linux
Classifier: Programming Language :: Python
Classifier: Programming Language :: Python :: 2
Classifier: Programming Language :: Python :: 2.7
Classifier: Programming Language :: Python :: 3
Classifier: Programming Language :: Python :: 3.6
Classifier: Programming Language :: Python :: 3.7
Requires-Dist: designate
Requires-Dist: neutron
